setup.py
pyeti/__init__.py
pyeti/stuff.py
pyeti.egg-info/PKG-INFO
pyeti.egg-info/SOURCES.txt
pyeti.egg-info/dependency_links.txt
pyeti.egg-info/not-zip-safe
pyeti.egg-info/top_level.txt