Metadata-Version: 1.0
Name: pyeti
Version: 0.1
Summary: The awesomest Python package from ETI
Home-page: https://github.com/cehdeti/pyeti
Author: ETI
Author-email: saun0063@umn.edu
License: MIT
Platform: UNKNOWN
